{"index.md":"67b9b983","web_breadth.md":"eb2ecb9f","web_career-planning.md":"1348e13a","web_algorithm.md":"09c6e09f","web_performance.md":"b43a9b3c","web_knowledge.md":"8a476e26","web_depth.md":"7ca93845","web_other.md":"a09b3efa","web_code-output.md":"25820caf","web_experience.md":"2f7c61cb","web_hr.md":"122ba771","web_html.md":"81b0642c","web_network.md":"1dc65aca","web_browser.md":"0febc004","web_javascript.md":"bb34cc1b","web_css.md":"ce9ee1b3","web_introduction.md":"6b0515b7","web_vue.md":"11d01e3a","web_resolve.md":"8bed339e","web_program.md":"cba28a0e","web_project-design.md":"6df753cd","web_project.md":"e0a0505f","web_react.md":"3df020d9","web_skills.md":"8ffdd5bc","web_soft-skill.md":"ca6ed0df","web_typescript.md":"0f0f2600"}
