{"index.md":"d57bd2e8","web_browser.md":"73289e54","web_breadth.md":"d1b64dd0","web_career-planning.md":"7c5fe0dd","web_soft-skill.md":"a2f13b6c","web_algorithm.md":"03eeb045","web_other.md":"fe5d3754","web_css.md":"2bd5c099","web_depth.md":"d7a27255","web_experience.md":"2c160115","web_introduction.md":"958e8a5d","web_project-process.md":"00396dfe","web_knowledge.md":"24193d06","web_html.md":"147a4b91","web_skills.md":"1ee17baf","web_network.md":"6f10487a","web_project-design.md":"2f402664","web_typescript.md":"f4ae6810","web_javascript.md":"09b5abdc","web_hr.md":"e473d10c","web_code-quality.md":"6c27ae55","web_project.md":"15b34daf","web_micro-frontends.md":"b7e37ca4","web_vue.md":"bc5c76d2","web_resume.md":"aac95a11","web_resolve.md":"611a3efd","web_performance.md":"d28e451a","web_code-output.md":"07750cc8","web_react.md":"44f80567","web_program.md":"fb31400d"}
